{"version": "1", "message": "ERROR: Hidden Testcases server unreachable.", "problem_id": "ads2_m10_a1_1", "user_id": "saad181", "score": {"sample": {"0": {"execution_time": 0.6084012985229492, "passed": true}, "1": {"execution_time": 0.5760245323181152, "passed": true}, "2": {"execution_time": 0.4823784828186035, "passed": true}, "3": {"execution_time": 0.18557167053222656, "passed": true}, "4": {"execution_time": 1.1020746231079102, "passed": true}, "5": {"execution_time": 1.1048002243041992, "passed": true}, "6": {"execution_time": 4.151463747024536, "passed": true}, "7": {"execution_time": 0.5592548847198486, "passed": true}, "8": {"execution_time": 3.076941728591919, "passed": true}}}, "check_style_score": "1/1"}